{"repo": {"timestamp": 1751561511000}, "packages": {"com.keymatch.app": {"metadata": {"lastUpdated": 1751560767000, "preferredSigner": "76a456011df3378790168e8079603636e0b6e3f5ba0fe7a4e5f4ad48da15e02c"}, "versions": {"e18fb8f38251d315aeaf17fa3e0f5cf9cb45ead15c2c2c5baacbe6dc53ded2a9": null, "15bea551f3921a90aa23e3e80ebdb72ef24d195c861c3cf9f20a03c8c5ebf12a": {"added": 1751560767000, "file": {"name": "/com.keymatch.app_108.apk", "sha256": "15bea551f3921a90aa23e3e80ebdb72ef24d195c861c3cf9f20a03c8c5ebf12a", "size": 26310728}, "manifest": {"nativecode": ["arm64-v8a", "armeabi-v7a", "x86", "x86_64"], "versionName": "1.0.4", "versionCode": 108, "usesSdk": {"minSdkVersion": 21, "targetSdkVersion": 34}, "signer": {"sha256": ["76a456011df3378790168e8079603636e0b6e3f5ba0fe7a4e5f4ad48da15e02c"]}, "usesPermission": [{"name": "android.permission.CAMERA"}, {"name": "android.permission.READ_EXTERNAL_STORAGE"}, {"name": "android.permission.WRITE_EXTERNAL_STORAGE"}, {"name": "android.permission.READ_MEDIA_IMAGES"}, {"name": "android.permission.READ_MEDIA_VIDEO"}, {"name": "android.permission.INTERNET"}, {"name": "android.permission.ACCESS_FINE_LOCATION"}, {"name": "android.permission.ACCESS_COARSE_LOCATION"}, {"name": "com.android.vending.BILLING"}, {"name": "android.permission.VIBRATE"}, {"name": "android.permission.POST_NOTIFICATIONS"}, {"name": "android.permission.ACCESS_NETWORK_STATE"}, {"name": "com.keymatch.app.DYNAMIC_RECEIVER_NOT_EXPORTED_PERMISSION"}]}}, "9499a1243635fdb8be4e1e98e7bfb82425e435bb7ce6c824723fdde921f62442": {"added": 1751556441000, "file": {"name": "/com.keymatch.app_107.apk", "sha256": "9499a1243635fdb8be4e1e98e7bfb82425e435bb7ce6c824723fdde921f62442", "size": 26307972}, "manifest": {"nativecode": ["arm64-v8a", "armeabi-v7a", "x86", "x86_64"], "versionName": "1.0.3", "versionCode": 107, "usesSdk": {"minSdkVersion": 21, "targetSdkVersion": 34}, "signer": {"sha256": ["76a456011df3378790168e8079603636e0b6e3f5ba0fe7a4e5f4ad48da15e02c"]}, "usesPermission": [{"name": "android.permission.CAMERA"}, {"name": "android.permission.READ_EXTERNAL_STORAGE"}, {"name": "android.permission.WRITE_EXTERNAL_STORAGE"}, {"name": "android.permission.READ_MEDIA_IMAGES"}, {"name": "android.permission.READ_MEDIA_VIDEO"}, {"name": "android.permission.INTERNET"}, {"name": "android.permission.ACCESS_FINE_LOCATION"}, {"name": "android.permission.ACCESS_COARSE_LOCATION"}, {"name": "com.android.vending.BILLING"}, {"name": "android.permission.VIBRATE"}, {"name": "android.permission.POST_NOTIFICATIONS"}, {"name": "android.permission.ACCESS_NETWORK_STATE"}, {"name": "com.keymatch.app.DYNAMIC_RECEIVER_NOT_EXPORTED_PERMISSION"}]}}}}}}